django_develop/__init__.py
django_develop/cli.py
django_develop/dev_settings.py
django_develop/dev_urls.py
django_develop/utils.py
django_develop-0.1.dist-info/DESCRIPTION.rst
django_develop-0.1.dist-info/METADATA
django_develop-0.1.dist-info/RECORD
django_develop-0.1.dist-info/WHEEL
django_develop-0.1.dist-info/entry_points.txt
django_develop-0.1.dist-info/metadata.json
django_develop-0.1.dist-info/top_level.txt
