Metadata-Version: 2.0
Name: django-develop
Version: 0.1
Summary: Django development for humans
Home-page: https://github.com/pjdelport/django-develop
Author: Pi Delport
Author-email: pjdelport@gmail.com
License: UNKNOWN
Platform: UNKNOWN
Classifier: Development Status :: 3 - Alpha
Classifier: Environment :: Web Environment
Classifier: Framework :: Django
Classifier: Intended Audience :: Developers
Classifier: License :: Public Domain
Classifier: Programming Language :: Python :: 2
Classifier: Programming Language :: Python :: 3
Classifier: Topic :: Internet :: WWW/HTTP
Classifier: Topic :: Utilities
Requires-Dist: attrs (>=15.2.0)
Requires-Dist: Django
Requires-Dist: configparser
Requires-Dist: pathlib
